README.md
setup.cfg
setup.py
fstring/__init__.py
fstring/fstring.py
fstring.egg-info/PKG-INFO
fstring.egg-info/SOURCES.txt
fstring.egg-info/dependency_links.txt
fstring.egg-info/not-zip-safe
fstring.egg-info/top_level.txt