Metadata-Version: 1.1
Name: fstring
Version: 1.6
Summary: Working with strings has never been prettier.
Home-page: https://github.com/d-kiss/fstring
Author: Dan Elkis
Author-email: elkissdan@gmail.com
License: MIT
Keywords: string,fstring,formatting,inline,evaluation
Platform: UNKNOWN
Classifier: License :: OSI Approved :: MIT License
Classifier: Operating System :: OS Independent
Classifier: Programming Language :: Python
Classifier: Programming Language :: Python :: 2
Classifier: Programming Language :: Python :: 2.7
Classifier: Programming Language :: Python :: 3
Classifier: Programming Language :: Python :: 3.4
Classifier: Programming Language :: Python :: 3.5
Classifier: Programming Language :: Python :: 3.6
Classifier: Programming Language :: Python :: Implementation :: CPython
Classifier: Programming Language :: Python :: Implementation :: PyPy
